desw_dash.py
setup.py
DeSW_Dash.egg-info/PKG-INFO
DeSW_Dash.egg-info/SOURCES.txt
DeSW_Dash.egg-info/dependency_links.txt
DeSW_Dash.egg-info/requires.txt
DeSW_Dash.egg-info/top_level.txt
test/test_rpc.py