Metadata-Version: 1.1
Name: DeSW-Dash
Version: 0.0.2
Summary: Bitcoin plugin for the desw wallet platform.
Home-page: https://github.com/WalletGuild/desw-dash
Author: WalletGuild
Author-email: support@gitguild.com
License: MIT
Platform: UNKNOWN
Classifier: License :: OSI Approved :: MIT License
Classifier: Programming Language :: Python :: 2
Classifier: Topic :: Software Development :: Libraries
